wikimine/__about__.py
wikimine/__init__.py
wikimine/cli.py
wikimine/db.py
wikimine/entity.py
wikimine/extractor.py
wikimine/labels.py
wikimine/query.py
wikimine/relations.py
wikimine/utils.py
wikimine/wiki_link.py
wikimine/tasks/__init__.py
wikimine/tasks/unpack.py
wikimine/tasks/wikidata_dump.py
wikimine/tasks/wikidata_index.py
wikimine-0.0.9.dist-info/METADATA
wikimine-0.0.9.dist-info/WHEEL
wikimine-0.0.9.dist-info/licenses/LICENSE.txt
wikimine-0.0.9.dist-info/RECORD
